[{"id":2,"type":"room","numberOfRoom":1,"numberOfGuest":3,"location":{"latitude":19.444,"longitude":43.444,"adress":{"city":"Temerin","postNumber":21000,"street":"Ruza","streetNumber":"55"}},"dateForRenting":[{"dateFrom":1601330400000,"dateTo":1603317600000}],"freeDateForRenting":[1601330400000,1601416800000,1601503200000,1601589600000,1601676000000,1601762400000,1601848800000,1601935200000,1602021600000,1602108000000,1602194400000,1602280800000,1602367200000,1603144800000,1603231200000,1603317600000],"host":{"appartments":[],"username":"savo","password":"sa","name":"Savo","surname":"Tomic","gender":"male","isBlocked":false,"typeOfUser":"Host"},"comments":[],"pictures":["pictures\\2-1.png","pictures\\2-2.png","pictures\\2-3.png"],"priceForNight":1200.0,"checkInTime":"09:50","checkOutTime":"10:50","status":"active","amenities":[{"id":4,"name":"WiFi","deleted":false}],"reservations":[{"id":4,"guest":{"rentedAppartments":[],"reservations":[{"id":1,"appartment":{"id":1,"type":"apartment","numberOfRoom":2,"numberOfGuest":4,"location":{"latitude":19.444,"longitude":43.444,"adress":{"city":"Novi Sad","postNumber":21000,"street":"Djordja Rajkovica","streetNumber":"6"}},"dateForRenting":[{"dateFrom":1600466400000,"dateTo":1601416800000}],"freeDateForRenting":[1600466400000,1600552800000,1600639200000,1601071200000,1601157600000,1601244000000,1601330400000,1601416800000],"host":{"appartments":[],"username":"savo","password":"sa","name":"Savo","surname":"Tomic","gender":"male","isBlocked":false,"typeOfUser":"Host"},"comments":[],"pictures":["pictures\\1-1.png","pictures\\1-2.png"],"priceForNight":3500.0,"checkInTime":"09:50","checkOutTime":"11:00","status":"active","amenities":[{"id":2,"name":"Frizider","deleted":false},{"id":4,"name":"WiFi","deleted":false}],"deleted":false},"startDate":1600725600000,"daysForStay":3,"price":13650.0,"message":"","status":"canceled"},{"id":2,"appartment":{"id":1,"type":"apartment","numberOfRoom":2,"numberOfGuest":4,"location":{"latitude":19.444,"longitude":43.444,"adress":{"city":"Novi Sad","postNumber":21000,"street":"Djordja Rajkovica","streetNumber":"6"}},"dateForRenting":[{"dateFrom":1600466400000,"dateTo":1601416800000}],"freeDateForRenting":[1600466400000,1600552800000,1600639200000,1601071200000,1601157600000,1601244000000,1601330400000,1601416800000],"host":{"appartments":[],"username":"savo","password":"sa","name":"Savo","surname":"Tomic","gender":"male","isBlocked":false,"typeOfUser":"Host"},"comments":[],"pictures":["pictures\\1-1.png","pictures\\1-2.png"],"priceForNight":3500.0,"checkInTime":"09:50","checkOutTime":"11:00","status":"active","amenities":[{"id":2,"name":"Frizider","deleted":false},{"id":4,"name":"WiFi","deleted":false}],"deleted":false},"startDate":1600725600000,"daysForStay":3,"price":13650.0,"message":"","status":"accepted"},{"id":3,"appartment":{"id":1,"type":"apartment","numberOfRoom":2,"numberOfGuest":4,"location":{"latitude":19.444,"longitude":43.444,"adress":{"city":"Novi Sad","postNumber":21000,"street":"Djordja Rajkovica","streetNumber":"6"}},"dateForRenting":[{"dateFrom":1600466400000,"dateTo":1601416800000}],"freeDateForRenting":[1600466400000,1600552800000,1600639200000,1601071200000],"host":{"appartments":[],"username":"savo","password":"sa","name":"Savo","surname":"Tomic","gender":"male","isBlocked":false,"typeOfUser":"Host"},"comments":[],"pictures":["pictures\\1-1.png","pictures\\1-2.png"],"priceForNight":3500.0,"checkInTime":"09:50","checkOutTime":"11:00","status":"active","amenities":[{"id":2,"name":"Frizider","deleted":false},{"id":4,"name":"WiFi","deleted":false}],"deleted":false},"startDate":1601157600000,"daysForStay":3,"price":13650.0,"message":"","status":"rejected"}],"username":"srdjan","password":"gost","name":"Srdjan","surname":"Tomic","gender":"male","isBlocked":false,"typeOfUser":"Guest"},"startDate":1602453600000,"daysForStay":7,"price":9240.0,"message":"","status":"created"}],"deleted":false},{"id":3,"type":"apartment","numberOfRoom":1,"numberOfGuest":2,"location":{"latitude":2.0,"longitude":2.0,"adress":{"city":"Novi Sad","postNumber":21000,"street":"Temerinska","streetNumber":"20"}},"dateForRenting":[{"dateFrom":1600466400000,"dateTo":1605308400000}],"freeDateForRenting":[1600466400000,1600552800000,1600639200000,1600725600000,1600812000000,1600898400000,1600984800000,1601071200000,1601157600000,1601244000000,1601330400000,1601416800000,1601676000000,1601762400000,1601848800000,1601935200000,1602021600000,1602108000000,1602194400000,1602280800000,1602367200000,1602453600000,1602540000000,1602626400000,1602712800000,1602799200000,1602885600000,1602972000000,1603058400000,1603144800000,1603231200000,1603317600000,1603404000000,1603490400000,1603576800000,1603663200000,1603749600000,1603836000000,1603922400000,1604008800000,1604095200000,1604181600000,1604268000000,1604354400000,1604440800000,1604527200000,1604613600000,1604700000000,1604786400000,1604872800000,1604959200000,1605045600000,1605132000000,1605218400000,1605304800000],"host":{"appartments":[],"username":"domacin1","password":"domacin","name":"Srdjan","surname":"Tomic","gender":"male","isBlocked":false,"typeOfUser":"Host"},"comments":[],"pictures":["pictures\\3-1.png","pictures\\3-2.png","pictures\\3-3.png"],"priceForNight":2500.0,"checkInTime":"12:00","checkOutTime":"12:00","status":"active","amenities":[{"id":2,"name":"Frizider","deleted":false},{"id":3,"name":"Kuhinja","deleted":false},{"id":4,"name":"WiFi","deleted":false}],"reservations":[{"id":5,"guest":{"reservations":[],"username":"gost1","password":"gost","name":"Savo","surname":"Tomic","gender":"male","isBlocked":false,"typeOfUser":"Guest"},"startDate":1601503200000,"daysForStay":1,"price":4750.0,"message":"","status":"created"}],"deleted":false},{"id":1,"type":"apartment","numberOfRoom":2,"numberOfGuest":4,"location":{"latitude":19.444,"longitude":43.444,"adress":{"city":"Novi Sad","postNumber":21000,"street":"Djordja Rajkovica","streetNumber":"6"}},"dateForRenting":[{"dateFrom":1600466400000,"dateTo":1601416800000},{"dateFrom":1602972000000,"dateTo":1603490400000}],"freeDateForRenting":[1600466400000,1600552800000,1600639200000,1601071200000,1601157600000,1601244000000,1601330400000,1601416800000,1602972000000,1603058400000,1603144800000,1603231200000,1603317600000,1603404000000,1603490400000],"host":{"appartments":[],"username":"savo","password":"sa","name":"Savo","surname":"Tomic","gender":"male","isBlocked":false,"typeOfUser":"Host"},"comments":[],"pictures":["pictures\\1-1.png","pictures\\1-2.png"],"priceForNight":3500.0,"checkInTime":"09:50","checkOutTime":"11:00","status":"active","amenities":[{"id":2,"name":"Frizider","deleted":false},{"id":4,"name":"WiFi","deleted":false}],"reservations":[{"id":1,"guest":{"rentedAppartments":[],"reservations":[],"username":"srdjan","password":"gost","name":"Srdjan","surname":"Tomic","gender":"male","isBlocked":false,"typeOfUser":"Guest"},"startDate":1600725600000,"daysForStay":3,"price":13650.0,"message":"","status":"canceled"},{"id":2,"guest":{"rentedAppartments":[],"reservations":[{"id":1,"appartment":{"id":1,"type":"apartment","numberOfRoom":2,"numberOfGuest":4,"location":{"latitude":19.444,"longitude":43.444,"adress":{"city":"Novi Sad","postNumber":21000,"street":"Djordja Rajkovica","streetNumber":"6"}},"dateForRenting":[{"dateFrom":1600466400000,"dateTo":1601416800000}],"freeDateForRenting":[1600466400000,1600552800000,1600639200000,1601071200000,1601157600000,1601244000000,1601330400000,1601416800000],"host":{"appartments":[],"username":"savo","password":"sa","name":"Savo","surname":"Tomic","gender":"male","isBlocked":false,"typeOfUser":"Host"},"comments":[],"pictures":["pictures\\1-1.png","pictures\\1-2.png"],"priceForNight":3500.0,"checkInTime":"09:50","checkOutTime":"11:00","status":"active","amenities":[{"id":2,"name":"Frizider","deleted":false},{"id":4,"name":"WiFi","deleted":false}],"deleted":false},"startDate":1600725600000,"daysForStay":3,"price":13650.0,"message":"","status":"canceled"}],"username":"srdjan","password":"gost","name":"Srdjan","surname":"Tomic","gender":"male","isBlocked":false,"typeOfUser":"Guest"},"startDate":1600725600000,"daysForStay":3,"price":13650.0,"message":"","status":"accepted"},{"id":3,"guest":{"rentedAppartments":[],"reservations":[{"id":1,"appartment":{"id":1,"type":"apartment","numberOfRoom":2,"numberOfGuest":4,"location":{"latitude":19.444,"longitude":43.444,"adress":{"city":"Novi Sad","postNumber":21000,"street":"Djordja Rajkovica","streetNumber":"6"}},"dateForRenting":[{"dateFrom":1600466400000,"dateTo":1601416800000}],"freeDateForRenting":[1600466400000,1600552800000,1600639200000,1601071200000,1601157600000,1601244000000,1601330400000,1601416800000],"host":{"appartments":[],"username":"savo","password":"sa","name":"Savo","surname":"Tomic","gender":"male","isBlocked":false,"typeOfUser":"Host"},"comments":[],"pictures":["pictures\\1-1.png","pictures\\1-2.png"],"priceForNight":3500.0,"checkInTime":"09:50","checkOutTime":"11:00","status":"active","amenities":[{"id":2,"name":"Frizider","deleted":false},{"id":4,"name":"WiFi","deleted":false}],"deleted":false},"startDate":1600725600000,"daysForStay":3,"price":13650.0,"message":"","status":"canceled"}],"username":"srdjan","password":"gost","name":"Srdjan","surname":"Tomic","gender":"male","isBlocked":false,"typeOfUser":"Guest"},"startDate":1601157600000,"daysForStay":3,"price":13650.0,"message":"","status":"rejected"}],"deleted":false}]